setup.py
moduleBAA2004/__init__.py
moduleBAA2004/one.py
moduleBAA2004/two.py
moduleBAA2004.egg-info/PKG-INFO
moduleBAA2004.egg-info/SOURCES.txt
moduleBAA2004.egg-info/dependency_links.txt
moduleBAA2004.egg-info/top_level.txt