Metadata-Version: 2.1
Name: moduleBAA2004
Version: 0.0.1
Summary: useless module
Author: Bultsev Alexander
Author-email: bultsevalexander@yandex.ru
